pyorthanc/__init__.py
pyorthanc/_filtering.py
pyorthanc/_find.py
pyorthanc/_internal_client.py
pyorthanc/_modality.py
pyorthanc/_orthanc_sdk_enums.py
pyorthanc/_resources/__init__.py
pyorthanc/_resources/instance.py
pyorthanc/_resources/patient.py
pyorthanc/_resources/resource.py
pyorthanc/_resources/series.py
pyorthanc/_resources/study.py
pyorthanc/_upload.py
pyorthanc/async_client.py
pyorthanc/client.py
pyorthanc/deprecated/__init__.py
pyorthanc/deprecated/client.py
pyorthanc/errors.py
pyorthanc/jobs.py
pyorthanc/orthanc_sdk.py
pyorthanc/retrieve.py
pyorthanc/util.py
pyorthanc-1.22.0.dist-info/LICENSE.txt
pyorthanc-1.22.0.dist-info/METADATA
pyorthanc-1.22.0.dist-info/WHEEL
pyorthanc-1.22.0.dist-info/RECORD
