Metadata-Version: 2.3
Name: pyorthanc
Version: 1.22.0
Summary: Orthanc REST API python wrapper with additional utilities
License: MIT
Keywords: Orthanc,DICOM,Medical-Imaging
Author: Gabriel Couture
Author-email: gacou54@gmail.com
Requires-Python: >=3.8,<4.0
Classifier: License :: OSI Approved :: MIT License
Classifier: Programming Language :: Python :: 3
Classifier: Programming Language :: Python :: 3.8
Classifier: Programming Language :: Python :: 3.9
Classifier: Programming Language :: Python :: 3.10
Classifier: Programming Language :: Python :: 3.11
Classifier: Programming Language :: Python :: 3.12
Classifier: Programming Language :: Python :: 3.13
Provides-Extra: all
Provides-Extra: progress
Requires-Dist: httpx (>=0.24.1,<1.0.0)
Requires-Dist: pydicom (>=2.3.0,<4.0.0)
Requires-Dist: tqdm (>=4.66.1,<5.0.0) ; extra == "progress" or extra == "all"
Project-URL: Homepage, https://gacou54.github.io/pyorthanc/
Project-URL: Repository, https://github.com/gacou54/pyorthanc
